rotalabs_audit/__init__.py
rotalabs_audit/_version.py
rotalabs_audit/analysis/__init__.py
rotalabs_audit/analysis/awareness.py
rotalabs_audit/analysis/causal.py
rotalabs_audit/analysis/counterfactual.py
rotalabs_audit/analysis/quality.py
rotalabs_audit/chains/__init__.py
rotalabs_audit/chains/confidence.py
rotalabs_audit/chains/parser.py
rotalabs_audit/chains/patterns.py
rotalabs_audit/core/__init__.py
rotalabs_audit/core/config.py
rotalabs_audit/core/exceptions.py
rotalabs_audit/core/types.py
rotalabs_audit/integration/__init__.py
rotalabs_audit/integration/comply.py
rotalabs_audit/tracing/__init__.py
rotalabs_audit/tracing/decision.py
rotalabs_audit/tracing/path.py
rotalabs_audit/utils/__init__.py
rotalabs_audit/utils/helpers.py
rotalabs_audit-1.0.0.dist-info/METADATA
rotalabs_audit-1.0.0.dist-info/WHEEL
rotalabs_audit-1.0.0.dist-info/licenses/LICENSE
rotalabs_audit-1.0.0.dist-info/RECORD
